sec_vault_generator/__init__.py
sec_vault_generator/args.py
sec_vault_generator/exceptions.py
sec_vault_generator/filters.py
sec_vault_generator/frontmatter.py
sec_vault_generator/gitlab.py
sec_vault_generator/globals.py
sec_vault_generator/jinja.py
sec_vault_generator/shortcuts.py
sec_vault_generator/tag.py
sec_vault_generator/util.py
sec_vault_generator/templates/__init__.py
sec_vault_generator/templates/macros.md
sec_vault_generator/templates/lolbas/__init__.py
sec_vault_generator/templates/lolbas/base.md
sec_vault_generator/templates/mitre_attack/__init__.py
sec_vault_generator/templates/mitre_attack/bullet_list.md
sec_vault_generator/templates/mitre_attack/data_component.md
sec_vault_generator/templates/mitre_attack/data_source.md
sec_vault_generator/templates/mitre_attack/malware.md
sec_vault_generator/templates/mitre_attack/tactic.md
sec_vault_generator/templates/mitre_attack/tactic_index.md
sec_vault_generator/templates/mitre_attack/technique.md
sec_vault_generator/templates/mitre_attack/tool.md
sec_vault_generator/templates/network_scan/__init__.py
sec_vault_generator/templates/network_scan/host.md
sec_vault_generator/templates/network_scan/hostname.md
sec_vault_generator/templates/network_scan/juncture_all_hostnames.md
sec_vault_generator/templates/network_scan/juncture_all_hosts.md
sec_vault_generator/templates/network_scan/juncture_host_hostnames.md
sec_vault_generator/templates/network_scan/juncture_host_ports.md
sec_vault_generator/templates/network_scan/juncture_host_services.md
sec_vault_generator/templates/network_scan/juncture_scripts.md
sec_vault_generator/templates/network_scan/juncture_services.md
sec_vault_generator/templates/network_scan/juncture_severities.md
sec_vault_generator/templates/network_scan/macros.template
sec_vault_generator/templates/network_scan/nessus_plugin.md
sec_vault_generator/templates/network_scan/nessus_vulnerability.md
sec_vault_generator/templates/network_scan/port.md
sec_vault_generator/utils/__init__.py
sec_vault_generator-0.0.0.dist-info/LICENSE
sec_vault_generator-0.0.0.dist-info/METADATA
sec_vault_generator-0.0.0.dist-info/WHEEL
sec_vault_generator-0.0.0.dist-info/top_level.txt
sec_vault_generator-0.0.0.dist-info/RECORD
