Metadata-Version: 2.1
Name: sec-vault-generator
Version: 0.0.0
Summary: A framework to parse common things into an Obsidian vault.
Home-page: https://github.com/arch4ngel/sec-vault-generator
Author: Justin Angel
Author-email: justin@arch4ngel.ninja
License: UNKNOWN
Platform: UNKNOWN
Classifier: Programming Language :: Python :: 3
Classifier: License :: OSI Approved :: MIT License
Classifier: Operating System :: POSIX :: Linux
Requires-Python: >=3.9
Requires-Dist: GitPython
Requires-Dist: Jinja2
Requires-Dist: parsuite
Requires-Dist: pyaml
Requires-Dist: requests
